pyp2req/__init__.py
pyp2req/__main__.py
pyp2req-0.1.1.dist-info/METADATA
pyp2req-0.1.1.dist-info/WHEEL
pyp2req-0.1.1.dist-info/entry_points.txt
pyp2req-0.1.1.dist-info/top_level.txt
pyp2req-0.1.1.dist-info/RECORD
