Metadata-Version: 2.1
Name: pyp2req
Version: 0.1.1
Summary: pyproject.toml to requirements.txt converter
Author-email: JCGoran <jcgoran@protonmail.com>
Project-URL: GitHub, https://github.com/JCGoran/pyp2req
Requires-Python: >=3.8
Requires-Dist: tomli ; python_version < "3.11"
